pyniva/__init__.py
pyniva/__version__.py
pyniva/get_data.py
pyniva/metaflow.py
pyniva/thing.py
pyniva/tsb.py
pyniva-0.4.3.dist-info/LICENSE.txt
pyniva-0.4.3.dist-info/METADATA
pyniva-0.4.3.dist-info/WHEEL
pyniva-0.4.3.dist-info/top_level.txt
pyniva-0.4.3.dist-info/RECORD
