Metadata-Version: 2.1
Name: pyniva
Version: 0.4.3
Summary: Python wrapper/API for interacting with NIVA's data platform
Home-page: https://github.com/NIVANorge/pyniva
Author: Zofia Rudjord
Author-email: zofia.rudjord@niva.no
License: MIT license
Keywords: metadata timeseries data
Platform: UNKNOWN
Classifier: Development Status :: 3 - Alpha
Classifier: Intended Audience :: Developers
Classifier: Programming Language :: Python :: 3
Classifier: Programming Language :: Python :: 3.5
Classifier: Programming Language :: Python :: 3.6
Classifier: Programming Language :: Python :: 3.7
Requires-Dist: pandas (<2.0,>=1.1)
Requires-Dist: numpy (<2.0,>=1.16)
Requires-Dist: requests (<3.0,>=2.20)
Requires-Dist: pyjwt (<2.0,>=1.7)
Requires-Dist: cryptography (<3.0,>=2.5)
